simpleelf/__init__.py
simpleelf/elf_builder.py
simpleelf/elf_consts.py
simpleelf/elf_structs.py
simpleelf-1.0.0.dist-info/METADATA
simpleelf-1.0.0.dist-info/WHEEL
simpleelf-1.0.0.dist-info/top_level.txt
simpleelf-1.0.0.dist-info/RECORD
