Metadata-Version: 2.1
Name: simpleelf
Version: 1.0.0
Summary: Simple ELF parser and builder
Author-email: doronz88 <doron88@gmail.com>
Maintainer-email: doronz88 <doron88@gmail.com>
Project-URL: Homepage, https://github.com/doronz88/simpleelf
Project-URL: Bug Reports, https://github.com/doronz88/simpleelf/issues
Keywords: elf,reverse-engineering,research
Classifier: Development Status :: 5 - Production/Stable
Classifier: License :: OSI Approved :: GNU General Public License v3 or later (GPLv3+)
Classifier: Programming Language :: Python :: 3
Classifier: Programming Language :: Python :: 3.8
Classifier: Programming Language :: Python :: 3.9
Classifier: Programming Language :: Python :: 3.10
Classifier: Programming Language :: Python :: 3.11
Classifier: Programming Language :: Python :: 3 :: Only
Requires-Python: >=3.8
Requires-Dist: construct >=2.10.54
Provides-Extra: test
Requires-Dist: pytest ; extra == 'test'
